[{"country_a": "CAN", "country_b": "RUS", "a_to_b_events": 539, "b_to_a_events": 382, "a_to_b_goldstein": -5.230055745324752, "b_to_a_goldstein": -4.7560210327827495, "goldstein_asymmetry": 0.4740347125420028, "volume_asymmetry": 157}, {"country_a": "RUS", "country_b": "UKR", "a_to_b_events": 77763, "b_to_a_events": 33590, "a_to_b_goldstein": -5.778861461060942, "b_to_a_goldstein": -5.359083134037073, "goldstein_asymmetry": 0.4197783270238693, "volume_asymmetry": 44173}, {"country_a": "JPN", "country_b": "RUS", "a_to_b_events": 423, "b_to_a_events": 786, "a_to_b_goldstein": -5.298818067455968, "b_to_a_goldstein": -5.069211273096293, "goldstein_asymmetry": 0.22960679435967446, "volume_asymmetry": 363}, {"country_a": "RUS", "country_b": "USA", "a_to_b_events": 12992, "b_to_a_events": 12912, "a_to_b_goldstein": -5.020597367964942, "b_to_a_goldstein": -5.221592394023432, "goldstein_asymmetry": 0.2009950260584903, "volume_asymmetry": 80}, {"country_a": "RUS", "country_b": "SWE", "a_to_b_events": 1666, "b_to_a_events": 478, "a_to_b_goldstein": -4.82352949591244, "b_to_a_goldstein": -5.015481261528685, "goldstein_asymmetry": 0.1919517656162455, "volume_asymmetry": 1188}, {"country_a": "GBR", "country_b": "RUS", "a_to_b_events": 4803, "b_to_a_events": 4767, "a_to_b_goldstein": -5.131209739714445, "b_to_a_goldstein": -5.27337955153161, "goldstein_asymmetry": 0.1421698118171646, "volume_asymmetry": 36}, {"country_a": "EUR", "country_b": "RUS", "a_to_b_events": 3819, "b_to_a_events": 9283, "a_to_b_goldstein": -5.302697141746727, "b_to_a_goldstein": -5.19821185494476, "goldstein_asymmetry": 0.10448528680196656, "volume_asymmetry": 5464}, {"country_a": "DEU", "country_b": "RUS", "a_to_b_events": 3285, "b_to_a_events": 3684, "a_to_b_goldstein": -5.319330370625767, "b_to_a_goldstein": -5.224538614643772, "goldstein_asymmetry": 0.09479175598199507, "volume_asymmetry": 399}, {"country_a": "POL", "country_b": "RUS", "a_to_b_events": 1388, "b_to_a_events": 2727, "a_to_b_goldstein": -5.412103826099583, "b_to_a_goldstein": -5.4747342012459255, "goldstein_asymmetry": 0.06263037514634284, "volume_asymmetry": 1339}, {"country_a": "NLD", "country_b": "RUS", "a_to_b_events": 394, "b_to_a_events": 295, "a_to_b_goldstein": -5.283756431589272, "b_to_a_goldstein": -5.328813625594317, "goldstein_asymmetry": 0.04505719400504482, "volume_asymmetry": 99}, {"country_a": "FRA", "country_b": "RUS", "a_to_b_events": 1628, "b_to_a_events": 1486, "a_to_b_goldstein": -5.136486578632045, "b_to_a_goldstein": -5.1127860793194575, "goldstein_asymmetry": 0.023700499312587553, "volume_asymmetry": 142}, {"country_a": "NOR", "country_b": "RUS", "a_to_b_events": 285, "b_to_a_events": 474, "a_to_b_goldstein": -4.874386056264242, "b_to_a_goldstein": -4.891983201232137, "goldstein_asymmetry": 0.017597144967895773, "volume_asymmetry": 189}]